cairo_math_64x61/__init__.py
cairo_math_64x61/hyp64x61.cairo
cairo_math_64x61/hyp64x61_mock.cairo
cairo_math_64x61/math64x61.cairo
cairo_math_64x61/math64x61_mock.cairo
cairo_math_64x61/trig64x61.cairo
cairo_math_64x61/trig64x61_mock.cairo
cairo_math_64x61/vec64x61.cairo
cairo_math_64x61/vec64x61_mock.cairo
cairo_math_64x61-2.1.1.dist-info/LICENSE
cairo_math_64x61-2.1.1.dist-info/METADATA
cairo_math_64x61-2.1.1.dist-info/WHEEL
cairo_math_64x61-2.1.1.dist-info/top_level.txt
cairo_math_64x61-2.1.1.dist-info/RECORD
