Metadata-Version: 2.1
Name: cairo_math_64x61
Version: 2.1.1
Summary: Fixed point 64.61 math library for Cairo / Starknet
Author-email: "Unstoppable Games, Inc." <info@unstoppablegames.io>
License: MIT License
Project-URL: Homepage, https://github.com/influenceth/cairo-math-64x61
Project-URL: Bug Tracker, https://github.com/influenceth/cairo-math-64x61/issues
Classifier: Programming Language :: Python :: 3
Classifier: License :: OSI Approved :: MIT License
Classifier: Operating System :: OS Independent
Requires-Python: >=3.9
License-File: LICENSE
